stac_pydantic/__init__.py
stac_pydantic/catalog.py
stac_pydantic/collection.py
stac_pydantic/extensions.py
stac_pydantic/item.py
stac_pydantic/item_collection.py
stac_pydantic/links.py
stac_pydantic/py.typed
stac_pydantic/shared.py
stac_pydantic/utils.py
stac_pydantic/version.py
stac_pydantic/api/__init__.py
stac_pydantic/api/collection.py
stac_pydantic/api/collections.py
stac_pydantic/api/conformance.py
stac_pydantic/api/item.py
stac_pydantic/api/item_collection.py
stac_pydantic/api/landing.py
stac_pydantic/api/links.py
stac_pydantic/api/search.py
stac_pydantic/api/version.py
stac_pydantic/api/extensions/__init__.py
stac_pydantic/api/extensions/fields.py
stac_pydantic/api/extensions/query.py
stac_pydantic/api/extensions/sort.py
stac_pydantic/api/utils/__init__.py
stac_pydantic/api/utils/link_factory.py
stac_pydantic/scripts/__init__.py
stac_pydantic/scripts/cli.py
stac_pydantic-3.5.0.dist-info/METADATA
stac_pydantic-3.5.0.dist-info/WHEEL
stac_pydantic-3.5.0.dist-info/entry_points.txt
stac_pydantic-3.5.0.dist-info/licenses/LICENSE
stac_pydantic-3.5.0.dist-info/RECORD
